{
  "id": "13de06a12131949f05",
  "tournamentId": "13de06a12131949f",
  "stageIndex": 0,
  "partIndex": 0,
  "matchIndex": 4,
  "playerA": {
    "playerId": "0220e2286ee13400",
    "nickname": "Lieil"
  },
  "playerB": {
    "playerId": "d77b152360b88e1e",
    "nickname": "MrPillow"
  },
  "bans": [
    {
      "banType": "team",
      "playerATeamId": "1109-1210-2602",
      "playerBTeamId": "1104-1202-1402"
    }
  ],
  "gameIds": [
    "13de06a12131949f0501",
    "13de06a12131949f0502",
    "13de06a12131949f0503"
  ],
  "video": "https://www.youtube.com/live/GKibbRTCCIA?t=15837"
}
