{
  "id": "b7f4346442601d8010",
  "tournamentId": "b7f4346442601d80",
  "stageIndex": 1,
  "partIndex": 0,
  "matchIndex": 1,
  "gameVersion": "3.8",
  "playerA": {
    "playerId": "47dce1226ff1f04d",
    "nickname": "浅冽"
  },
  "playerB": {
    "playerId": "a86dc1973d9552b2",
    "nickname": "丹青"
  },
  "gameIds": [
    "b7f4346442601d801001",
    "b7f4346442601d801002",
    "b7f4346442601d801003",
    "b7f4346442601d801004",
    "b7f4346442601d801005"
  ],
  "video": "https://www.bilibili.com/video/BV1oV4y1472A"
}
