{
  "id": "b837d5a69a36454d06",
  "tournamentId": "b837d5a69a36454d",
  "stageIndex": 0,
  "partIndex": 2,
  "matchIndex": 1,
  "playerA": {
    "playerId": "6e66ded15e9c53fd",
    "nickname": "饭团Fine"
  },
  "playerB": {
    "playerId": "54980de7c75538b6",
    "nickname": "葬送の鏡蓮華で"
  },
  "bans": [
    {
      "banType": "team",
      "playerATeamId": "1106-1203-1506",
      "playerBTeamId": "1201-1205-1601"
    }
  ],
  "gameIds": [
    "b837d5a69a36454d0601",
    "b837d5a69a36454d0602"
  ],
  "video": "https://www.bilibili.com/video/BV1464y177g9"
}
