{
  "id": "d495e5503feef26d12",
  "tournamentId": "d495e5503feef26d",
  "stageIndex": 1,
  "partIndex": 1,
  "matchIndex": 1,
  "gameVersion": "4.5",
  "playerA": {
    "playerId": "56d3fed378f51bce",
    "nickname": "弦聆aeon"
  },
  "playerB": {
    "playerId": "710be88085b08006",
    "nickname": "冰红茶心甘晴愿"
  },
  "bans": [
    {
      "banType": "team",
      "playerATeamId": "1203-1505-2102",
      "playerBTeamId": "1109-1210-2602"
    }
  ],
  "gameIds": [
    "d495e5503feef26d1201",
    "d495e5503feef26d1202",
    "d495e5503feef26d1203",
    "d495e5503feef26d1204"
  ],
  "video": "https://www.bilibili.com/video/BV1Nz421Z7Fn"
}
