{
  "id": "139908a4381ddce10402",
  "matchId": "139908a4381ddce104",
  "gameVersion": "3.7",
  "playerADeck": {
    "characters": [
      "2201",
      "1401",
      "1703"
    ],
    "teamId": "1401-1703-2201",
    "deckCode": "BCFR9BsQBEER9pYQClFx95gQDIHR+sMQDZEh/skQDdKBC8oRDbKRDPIREOIRD/MREPEB"
  },
  "playerBDeck": {
    "characters": [
      "2301",
      "2201",
      "1401"
    ],
    "teamId": "1401-2201-2301",
    "deckCode": "BSJy9zcRA1Ki+HURC2JS+rURDYIy/8QRDtMiBMoSDqOCDMsSDrOSDfMSEeMSEPQSEfIC"
  },
  "winner": "B",
  "starter": "B"
}
