{
  "id": "1dc4c42d8f8b95341007",
  "matchId": "1dc4c42d8f8b953410",
  "gameVersion": "4.8",
  "playerADeck": {
    "characters": [
      "1303",
      "2302",
      "2402"
    ],
    "teamId": "1303-2302-2402",
    "deckCode": "ATAw4zgOEUDg5E8PBEDw9JcPCVBw9r0PC2HQisMYDKFgC8YQDLGQDckQFvFxEToRDjAA"
  },
  "playerBDeck": {
    "characters": [
      "1210",
      "2602",
      "2103"
    ],
    "teamId": "1210-2103-2602",
    "deckCode": "FJDxyRYNFBAR0SoNEmCh1iwTCYBx9DAPE0AB9jMQE4ExCFcTC7HwO78YDKFAisQQDLAA"
  },
  "winner": "B",
  "starter": "A"
}
