{
  "id": "244c9d513f97f3070105",
  "matchId": "244c9d513f97f30701",
  "playerADeck": {
    "characters": [
      "1209",
      "2402",
      "2103"
    ],
    "teamId": "1209-2103-2402",
    "deckCode": "EZGBOEETEYDh20UPCWBw9pcQCoFBCDATE7EBOzEQE7EwC8YQDMFgDNURDQFQENkRDRAA"
  },
  "playerBDeck": {
    "characters": [
      "1202",
      "1104",
      "1402"
    ],
    "teamId": "1104-1202-1402",
    "deckCode": "AFBA1QoUAZGwSZcNE5AB2TATE4ERODMTE6Aw9MMPDECQ9ckQDIGgCMoTDbEQTNEUDcAA"
  },
  "winner": "A",
  "starter": "A"
}
