{
  "id": "3445b904efb0b6740201",
  "matchId": "3445b904efb0b67402",
  "gameVersion": "4.8",
  "playerADeck": {
    "characters": [
      "1305",
      "1209",
      "1111"
    ],
    "teamId": "1111-1209-1305",
    "deckCode": "AZBR2RgNFrCw8lEPCUBw9JcPE1AR9jEQFTFxO1cTGbExDJMQDMFgDcYQDNGgEMoRDQAA"
  },
  "playerBDeck": {
    "characters": [
      "1303",
      "2203",
      "2602"
    ],
    "teamId": "1303-2203-2602",
    "deckCode": "ARAxwV4MEUBgxE8MBJDxyWETEoGhOCoNCcBx9EgPFUBx9lcTGLEhO4IYC6FgirYQDLAA"
  },
  "winner": "B",
  "starter": "A"
}
