{
  "id": "3c8bf7110b0e4d7a1701",
  "matchId": "3c8bf7110b0e4d7a17",
  "playerADeck": {
    "characters": [
      "1104",
      "1407",
      "1107"
    ],
    "teamId": "1104-1107-1407",
    "deckCode": "AABA4AcOAuAA8ZcPCRBw9L0PC0DQ9cgPDFCA9skPDGCQ+M0QDKHQCtsQDbHwC98QDuAA"
  },
  "playerBDeck": {
    "characters": [
      "2201",
      "1401",
      "2301"
    ],
    "teamId": "1401-2201-2301",
    "deckCode": "ARCg8jUPAyBw9XMPCVBQ9pUPC2Aw+LMPC5DQ/cIQDKEgC8gQDLGADskQDOGQD/EQD/AA"
  },
  "winner": "A",
  "starter": "B"
}
