{
  "id": "55a3dccd1dcc1d740102",
  "matchId": "55a3dccd1dcc1d7401",
  "gameVersion": "4.4",
  "playerADeck": {
    "characters": [
      "1401",
      "1703",
      "1310"
    ],
    "teamId": "1310-1401-1703",
    "deckCode": "AZCg2TETEYGQOJcNCdBx9TAPE2AB9jMQE4ExCDQTE7FBOzYQE6FgC8MQDbFQEdURDTAA"
  },
  "playerBDeck": {
    "characters": [
      "1401",
      "1703",
      "1310"
    ],
    "teamId": "1310-1401-1703",
    "deckCode": "AZCg2TETEYGQOJcNCdBw9aQPE1AB9jAPE2ExCDMQE4FBOzYTE7FgC8MQDbFQEdURDTAA"
  },
  "winner": "B",
  "starter": "A"
}
