{
  "id": "8480e1ee29f1171b0402",
  "matchId": "8480e1ee29f1171b04",
  "gameVersion": "4.5",
  "playerADeck": {
    "characters": [
      "2403",
      "2602",
      "1303"
    ],
    "teamId": "1303-2403-2602",
    "deckCode": "AVExSUIUEZBh2SoNEpGgOJcTE4EBWTAVE5Ax3DMPDEAw9MkQDIGQCNETDbEQTNUUDcAA"
  },
  "playerBDeck": {
    "characters": [
      "1209",
      "2402",
      "2103"
    ],
    "teamId": "1209-2103-2402",
    "deckCode": "EZGBOEETEYDh20UPCWBw9pcQE4EBCDATE7EROzMQE7EwC8YQDMFgDNURDQFQENkRDRAA"
  },
  "winner": "B",
  "starter": "B"
}
