{
  "id": "964e20f8443917cd0105",
  "matchId": "964e20f8443917cd01",
  "playerADeck": {
    "characters": [
      "1605",
      "1201",
      "1602"
    ],
    "teamId": "1201-1602-1605",
    "deckCode": "AJCQ6isOAqDg7XwOB9DA8YgPCBCA9bMPC1Aw9rkPC9GQArwQCyHQC8kQDbGgDukQDuAA"
  },
  "playerBDeck": {
    "characters": [
      "1408",
      "1703",
      "1203"
    ],
    "teamId": "1203-1408-1703",
    "deckCode": "ABCw8iEPAyAQ9JcPCUBw9b0PDFCA9sgPDJCQ+ckQDaEgCtIQDbGwC+0QDuHQDvERDzAA"
  },
  "winner": "B",
  "starter": "B"
}
