{
  "id": "9eb952efd4ba2f191004",
  "matchId": "9eb952efd4ba2f1910",
  "gameVersion": "4.3",
  "playerADeck": {
    "characters": [
      "1203",
      "2402",
      "2102"
    ],
    "teamId": "1203-2102-2402",
    "deckCode": "AFCx2R4TEYFROCgNEuCA9ZcPCVBw9qQQE4EBCDATE7ExOzMQE6FBCzYQE7FgEdURDTAA"
  },
  "playerBDeck": {
    "characters": [
      "1209",
      "2402",
      "2102"
    ],
    "teamId": "1209-2102-2402",
    "deckCode": "EnGC2h8UEoFS3CkQE1GB95gQCmJyCTERFIICPDIRFKIxC8cRDcJhDdISDgJREdYSDhEB"
  },
  "winner": "A",
  "starter": "B"
}
