{
  "id": "9eb952efd4ba2f190803",
  "matchId": "9eb952efd4ba2f1908",
  "gameVersion": "4.3",
  "playerADeck": {
    "characters": [
      "1401",
      "1703",
      "1310"
    ],
    "teamId": "1310-1401-1703",
    "deckCode": "EYGQOBoNA+AQ9ZcPCWBx9jAQE4EBCDMTE7FBOzQQDKFgC8YQDbFQDtUQDeGQEdkREzAA"
  },
  "playerBDeck": {
    "characters": [
      "1401",
      "1703",
      "1310"
    ],
    "teamId": "1310-1401-1703",
    "deckCode": "EZGQOBoNA+AQ9ZcPCWBx9jAQE4EBCDMTE7FBOzQQE6FhCzYQDLFgDcYQDeFQEdURDTAA"
  },
  "winner": "B",
  "starter": "A"
}
