{
  "id": "a14968e1d32e88521301",
  "matchId": "a14968e1d32e885213",
  "gameVersion": "3.7",
  "playerADeck": {
    "characters": [
      "1303",
      "1306",
      "2401"
    ],
    "teamId": "1303-1306-2401",
    "deckCode": "AkEx7hcPBNGR8lAQBRHx85gQCiFx9rQQDFEx98MQDWEh/soQDeKRDOQRD7IxD+URD+EB"
  },
  "playerBDeck": {
    "characters": [
      "2201",
      "1401",
      "2301"
    ],
    "teamId": "1401-2201-2301",
    "deckCode": "BCFR9RsQBEFx9nQQClFR97QQDIEx+boQDNKRC74RDaIhDMMRDbKRD8oREOIREPIREPEB"
  },
  "winner": "A",
  "starter": "B"
}
