{
  "id": "b5ab736c62c28bfe2603",
  "matchId": "b5ab736c62c28bfe26",
  "playerADeck": {
    "characters": [
      "1303",
      "2602",
      "1403"
    ],
    "teamId": "1303-1403-2602",
    "deckCode": "AWAwxBwMEUBgyU8MBJDx3ioPCVAA9ZcPCWBx9jAQE4EBCDQTE7FAC8EQDLERETYREzAA"
  },
  "playerBDeck": {
    "characters": [
      "1309",
      "1508",
      "1502"
    ],
    "teamId": "1309-1502-1508",
    "deckCode": "AWCQySUMEZCh0SMNCRAA3pEOEnDw550OCYDR6DQQE7FBCzYQDOEgDsUQDPFQD8YRDDAA"
  },
  "winner": "B",
  "starter": "A"
}
