{
  "id": "c20763c9aa8dd0211203",
  "matchId": "c20763c9aa8dd02112",
  "gameVersion": "4.1",
  "playerADeck": {
    "characters": [
      "2201",
      "2301",
      "1408"
    ],
    "teamId": "1408-2201-2301",
    "deckCode": "A0BQ9TcPAlAQ9nMPCYBQ+JUPC9DA/bwQDKEgC8YQDLFgDckQDNGQDtcQDeHQD/QQD/AA"
  },
  "playerBDeck": {
    "characters": [
      "2201",
      "1401",
      "1703"
    ],
    "teamId": "1401-1703-2201",
    "deckCode": "AxBQ8RoPA0AQ9ZUPCVCw9sIPDIAg+cYPDNBg/ckQDKGQC9EQDbEQDtIQDfFwD90RDxAA"
  },
  "winner": "B",
  "starter": "A"
}
