{
  "id": "cb5496669221a1e11204",
  "matchId": "cb5496669221a1e112",
  "gameVersion": "4.2",
  "playerADeck": {
    "characters": [
      "2201",
      "1401",
      "2301"
    ],
    "teamId": "1401-2201-2301",
    "deckCode": "A1BQ3hoPA0Bw9ZsPClAw9qMPCoBw+KcQDIEgCMIQDKFgCsYQDLGQC8kQDeEQDtEQDfAA"
  },
  "playerBDeck": {
    "characters": [
      "1405",
      "1104",
      "1402"
    ],
    "teamId": "1104-1402-1405",
    "deckCode": "AZDg2QQNAbCw5UAOBFAA9JcPCUBw9cIQDCEgA8YQDDFgC8kQDMGgDMoQDdEQENERDQAA"
  },
  "winner": "B",
  "starter": "B"
}
