{
  "id": "d9400ab157fa158b0203",
  "matchId": "d9400ab157fa158b02",
  "gameVersion": "4.4",
  "playerADeck": {
    "characters": [
      "1408",
      "1103",
      "1403"
    ],
    "teamId": "1103-1403-1408",
    "deckCode": "AoEQOAMNAdDA5ZcOCVBw5qQOCmBB8TMPEyAw8r0PC1DR9jUPDGGQO8kTDbGQCtkQE7AA"
  },
  "playerBDeck": {
    "characters": [
      "1203",
      "2402",
      "2102"
    ],
    "teamId": "1203-2102-2402",
    "deckCode": "ABCx0R4NEVBR1SgTEqCA9ZcPCmFBCDAQE4EBOzQQE6FAC8IQDLFgDcYQDNGQEckRDTAA"
  },
  "winner": "B",
  "starter": "B"
}
