{
  "id": "e1465b96425236e30203",
  "matchId": "e1465b96425236e302",
  "gameVersion": "4.5",
  "playerADeck": {
    "characters": [
      "1104",
      "1202",
      "1402"
    ],
    "teamId": "1104-1202-1402",
    "deckCode": "AFBA1QoUAZGwSZcNE5AB2TATE4ERODMTE6Aw9MMPDFGQCMkQDIGgO8oTDbEQTNEUDcAA"
  },
  "playerBDeck": {
    "characters": [
      "1203",
      "1501",
      "1106"
    ],
    "teamId": "1106-1203-1501",
    "deckCode": "AJCw2SQNAJFgOJcTCYGBWTAVE5EBOjMPE0Aw9MkPDGGQCNEQDYEQO9UUDcFRTEkRFBAA"
  },
  "winner": "A",
  "starter": "B"
}
