{
  "id": "794b69f38812f7c7",
  "name": {
    "zh": "寒天之钉杯"
  },
  "gameVersion": "4.7",
  "type": "积分赛",
  "stages": [
    {
      "name": {
        "zh": "8进4"
      },
      "rules": {
        "numGames": 5,
        "mode": "conquest",
        "submitTeams": {
          "num": 4,
          "numCharactersRequired": 11,
          "banTeams": {
            "num": 1
          }
        }
      },
      "parts": [
        {
          "name": {
            "zh": "DAY1"
          },
          "date": "2024-06-26",
          "matchIds": [
            "794b69f38812f7c701",
            "794b69f38812f7c702"
          ]
        }
      ]
    }
  ]
}
